mermaid_magic.py
mermaid_magic-0.1.4.dist-info/METADATA
mermaid_magic-0.1.4.dist-info/WHEEL
mermaid_magic-0.1.4.dist-info/top_level.txt
mermaid_magic-0.1.4.dist-info/RECORD
