Metadata-Version: 2.4
Name: mermaid-magic
Version: 0.1.4
Summary: IPython magic for rendering Mermaid diagrams
Author: Vijay Balasubramaniam
Author-email: vbalasu@gmail.com
Project-URL: Source, https://github.com/vbalasu/mermaid-magic
Project-URL: Bug Reports, https://github.com/vbalasu/mermaid-magic/issues
Classifier: Development Status :: 3 - Alpha
Classifier: Intended Audience :: Developers
Classifier: License :: OSI Approved :: MIT License
Classifier: Programming Language :: Python :: 3
Classifier: Programming Language :: Python :: 3.6
Classifier: Programming Language :: Python :: 3.7
Classifier: Programming Language :: Python :: 3.8
Classifier: Programming Language :: Python :: 3.9
Requires-Dist: ipython
Dynamic: author
Dynamic: author-email
Dynamic: classifier
Dynamic: description
Dynamic: description-content-type
Dynamic: project-url
Dynamic: requires-dist
Dynamic: summary
